pyleebounds/__init__.py
pyleebounds/lee_bounds.py
pyleebounds-0.3.0.dist-info/licenses/LICENSE
pyleebounds-0.3.0.dist-info/METADATA
pyleebounds-0.3.0.dist-info/WHEEL
pyleebounds-0.3.0.dist-info/top_level.txt
pyleebounds-0.3.0.dist-info/RECORD
